README.md
dateformat.py
setup.py
dateformat.egg-info/PKG-INFO
dateformat.egg-info/SOURCES.txt
dateformat.egg-info/dependency_links.txt
dateformat.egg-info/requires.txt
dateformat.egg-info/top_level.txt