Metadata-Version: 2.1
Name: dateformat
Version: 0.9.6
Summary: Parse and format dates quickly
Home-page: https://github.com/stestagg/dateformat
Author: Stephen Stagg
Author-email: ste@sta.gg
License: MIT
Keywords: date time parsing formatting datetime
Platform: UNKNOWN
Classifier: Development Status :: 3 - Alpha
Classifier: Intended Audience :: Developers
Classifier: Topic :: Software Development :: Build Tools
Classifier: License :: OSI Approved :: MIT License
Classifier: Programming Language :: Python :: 3
Classifier: Programming Language :: Python :: 3.3
Classifier: Programming Language :: Python :: 3.4
Classifier: Programming Language :: Python :: 3.5
Provides-Extra: test
